pyprotoclust/__init__.py
pyprotoclust/__version__.py
pyprotoclust/c_protoclust.cpp
pyprotoclust/c_protoclust.pxd
pyprotoclust/c_protoclust.pyx
pyprotoclust/cpp/include/chain.h
pyprotoclust/cpp/include/linkage.h
pyprotoclust/cpp/include/ltmatrix.h
pyprotoclust/cpp/include/protoclust.h
pyprotoclust/cpp/src/chain.cpp
pyprotoclust/cpp/src/linkage.cpp
pyprotoclust/cpp/src/ltmatrix.cpp
pyprotoclust/cpp/src/protoclust.cpp
pyprotoclust/protoclust.py
pyprotoclust/c_protoclust.cp37-win_amd64.pyd
pyprotoclust-0.1.0.dist-info/WHEEL
pyprotoclust-0.1.0.dist-info/METADATA
pyprotoclust-0.1.0.dist-info/RECORD
