Metadata-Version: 2.1
Name: pyprotoclust
Version: 0.1.0
Summary: Hierarchical clustering using minimax linkage.
Home-page: https://github.com/andgoldschmidt/pyprotoclust
License: MIT
Keywords: hierarchical,clustering,minimax,prototypes
Author: Andy Goldschmidt
Author-email: andygold@uw.edu
Requires-Python: >=3.7,<4.0
Classifier: License :: OSI Approved :: MIT License
Classifier: Programming Language :: Python :: 3
Classifier: Programming Language :: Python :: 3.10
Classifier: Programming Language :: Python :: 3.7
Classifier: Programming Language :: Python :: 3.8
Classifier: Programming Language :: Python :: 3.9
Provides-Extra: cython
Provides-Extra: docs
Requires-Dist: cython (>=0.29.17,<0.30.0); extra == "cython"
Requires-Dist: ipykernel (>=5.2.1,<6.0.0); extra == "docs"
Requires-Dist: ipywidgets (>=7.5.1,<8.0.0); extra == "docs"
Requires-Dist: jupyter_client (>=6.1.3,<7.0.0); extra == "docs"
Requires-Dist: matplotlib (>=3.2.1,<4.0.0); extra == "docs"
Requires-Dist: nbsphinx (>=0.8.6,<0.9.0); extra == "docs"
Requires-Dist: scipy (>=1.4.1,<2.0.0); extra == "docs"
Requires-Dist: sklearn (>=0.0,<0.1); extra == "docs"
Requires-Dist: sphinx (>=3.0.3,<4.0.0); extra == "docs"
Requires-Dist: sphinx_rtd_theme (>=0.4.3,<0.5.0); extra == "docs"
Requires-Dist: tqdm (>=4.46.0,<5.0.0)
Project-URL: Documentation, https://pyprotoclust.readthedocs.io/
Project-URL: Repository, https://github.com/andgoldschmidt/pyprotoclust
